{ 
  "graph": [], 
  "links": [		{"source": 0, "target": 3},		{"source": 0, "target": 4},		{"source": 0, "target": 5},		{"source": 1, "target": 3},		{"source": 1, "target": 4},		{"source": 1, "target": 5},		{"source": 2, "target": 3},		{"source": 3, "target": 4},		{"source": 3, "target": 5},		{"source": 3, "target": 6},		{"source": 3, "target": 7},		{"source": 3, "target": 8},		{"source": 4, "target": 6},		{"source": 4, "target": 7},		{"source": 4, "target": 9},		{"source": 5, "target": 6},		{"source": 5, "target": 7},		{"source": 5, "target": 8},		{"source": 5, "target": 9},		{"source": 7, "target": 8},		{"source": 7, "target": 8}	],   "nodes": [		{"size": 3, "score": 1, "id": "0","type": "circle"},		{"size": 3, "score": 1, "id": "1","type": "circle"},		{"size": 1, "score": 1, "id": "2","type": "circle"},		{"size": 8, "score": 0, "id": "3","type": "circle"},		{"size": 6, "score": 0, "id": "4","type": "circle"},		{"size": 7, "score": 0, "id": "5","type": "circle"},		{"size": 3, "score": 1, "id": "6","type": "circle"},		{"size": 5, "score": 1, "id": "7","type": "circle"},		{"size": 3, "score": 1, "id": "8","type": "circle"},		{"size": 3, "score": 1, "id": "9","type": "circle"}	], 
 "directed": false, 
 "multigraph": false 
}